smallder/__init__.py
smallder/api/__init__.py
smallder/api/app.py
smallder/commands/__init__.py
smallder/commands/cmdline.py
smallder/commands/create.py
smallder/core/__init__.py
smallder/core/connection.py
smallder/core/customsignalmanager.py
smallder/core/downloader.py
smallder/core/dupfilter.py
smallder/core/engine.py
smallder/core/error.py
smallder/core/failure.py
smallder/core/item.py
smallder/core/middleware.py
smallder/core/request.py
smallder/core/response.py
smallder/core/scheduler.py
smallder/core/spider.py
smallder/core/statscollectors.py
smallder/templates/spider_template.tmpl
smallder/utils/__init__.py
smallder/utils/curl.py
smallder/utils/request.py
smallder/utils/utils.py
smallder-0.0.1.dist-info/METADATA
smallder-0.0.1.dist-info/WHEEL
smallder-0.0.1.dist-info/entry_points.txt
smallder-0.0.1.dist-info/top_level.txt
smallder-0.0.1.dist-info/RECORD
