Metadata-Version: 2.1
Name: smallder
Version: 0.0.1
Summary: An out-of-the-box lightweight asynchronous crawler framework
Author: NTrash
Author-email: yinghui0214@163.com
License: MIT
Classifier: Programming Language :: Python :: 3
Classifier: Programming Language :: Python :: 3.7
Classifier: License :: OSI Approved :: MIT License
Classifier: Operating System :: OS Independent
Requires-Python: >=3.7
Requires-Dist: annotated-types
Requires-Dist: anyio
Requires-Dist: async-timeout
Requires-Dist: certifi
Requires-Dist: chardet
Requires-Dist: charset-normalizer
Requires-Dist: click
Requires-Dist: colorama
Requires-Dist: exceptiongroup
Requires-Dist: fastapi
Requires-Dist: greenlet
Requires-Dist: h11
Requires-Dist: idna
Requires-Dist: loguru
Requires-Dist: pydantic
Requires-Dist: pydantic-core
Requires-Dist: PyDispatcher
Requires-Dist: redis
Requires-Dist: requests
Requires-Dist: six
Requires-Dist: sniffio
Requires-Dist: SQLAlchemy
Requires-Dist: starlette
Requires-Dist: typing-extensions
Requires-Dist: urllib3
Requires-Dist: uvicorn
Requires-Dist: w3lib
Requires-Dist: PyMySQL
